{"id":"16022","players":[{"id":"401910","name":"Iván Moreno","position":"Goalkeeper","dateOfBirth":"Oct 14, 1995","age":"28","nationality":["Spain"],"height":"1,84m","foot":"right","joinedOn":"Jul 9, 2023","signedFrom":"CP Cacereño","contract":"Jun 30, 2025","marketValue":"€150k"},{"id":"336733","name":"Jero Lario","position":"Goalkeeper","dateOfBirth":"Feb 7, 1995","age":"29","nationality":["Spain"],"height":"1,83m","foot":"right","joinedOn":"Jul 1, 2024","joined":"Joined from CD Atlético Baleares; date: Jul 1, 2024; fee: free transfer","signedFrom":"CD Atlético Baleares","contract":"Jun 30, 2025","marketValue":"€150k"},{"id":"1061332","name":"Dani Alcover","position":"Goalkeeper","dateOfBirth":"Apr 3, 2004","age":"20","nationality":["Spain"],"joinedOn":"Jul 11, 2024","joined":"Joined from CD Roda; date: Jul 11, 2024; fee: free transfer","signedFrom":"CD Roda","contract":"Jun 30, 2025"},{"id":"632080","name":"Franck Fomeyem","position":"Centre-Back","dateOfBirth":"Oct 17, 1999","age":"24","nationality":["Cameroon"],"height":"1,81m","foot":"right","joinedOn":"Jul 22, 2023","signedFrom":"UD San Sebastián de los Reyes","contract":"Jun 30, 2025","marketValue":"€300k"},{"id":"628882","name":"Luismi Luengo","position":"Centre-Back","dateOfBirth":"Mar 19, 2001","age":"23","nationality":["Spain"],"height":"1,85m","foot":"right","joinedOn":"Jul 1, 2024","joined":"Joined from Zamora CF; date: Jul 1, 2024; fee: free transfer","signedFrom":"Zamora CF","contract":"Jun 30, 2025","marketValue":"€250k"},{"id":"278467","name":"Iván Pérez","position":"Centre-Back","dateOfBirth":"Apr 12, 1993","age":"31","nationality":["Spain"],"height":"1,80m","foot":"right","joinedOn":"Jul 1, 2024","joined":"Joined from Real Unión Club; date: Jul 1, 2024; fee: free transfer","signedFrom":"Real Unión Club","contract":"Jun 30, 2025","marketValue":"€200k"},{"id":"719723","name":"Juan Aspra","position":"Centre-Back","dateOfBirth":"Jul 30, 2002","age":"22","nationality":["Spain"],"height":"1,82m","foot":"left","joinedOn":"Jul 16, 2024","joined":"Joined from Marino Luanco; date: Jul 16, 2024; fee: free transfer","signedFrom":"Marino Luanco","contract":"Jun 30, 2025","marketValue":"€200k"},{"id":"628461","name":"Iker Recio","position":"Centre-Back","dateOfBirth":"Jun 17, 2001","age":"23","nationality":["Spain"],"height":"1,84m","foot":"left","joinedOn":"Jul 20, 2024","joined":"Joined from AD Alcorcón; date: Jul 20, 2024; fee: free transfer","signedFrom":"AD Alcorcón","contract":"Jun 30, 2025","marketValue":"€50k"},{"id":"396108","name":"Juanmi Carrión","position":"Left-Back","dateOfBirth":"Aug 26, 1997","age":"27","nationality":["Spain"],"height":"1,77m","foot":"left","joinedOn":"Jul 9, 2024","joined":"Joined from Real Murcia CF; date: Jul 9, 2024; fee: free transfer","signedFrom":"Real Murcia CF","contract":"Jun 30, 2025","marketValue":"€200k"},{"id":"960983","name":"Agus Moreno","position":"Left-Back","dateOfBirth":"Jan 1, 2005","age":"19","nationality":["Spain"],"joinedOn":"Jul 5, 2024","joined":"On loan from Betis Deportivo Balompié until Jun 30, 2025","signedFrom":"Betis Deportivo Balompié","contract":"Jun 30, 2025"},{"id":"284454","name":"Iván Rodríguez","position":"Right-Back","dateOfBirth":"Apr 30, 1996","age":"28","nationality":["Spain"],"height":"1,80m","foot":"right","joinedOn":"Jul 14, 2024","joined":"Joined from Córdoba CF; date: Jul 14, 2024; fee: free transfer","signedFrom":"Córdoba CF","contract":"Jun 30, 2025","marketValue":"€200k"},{"id":"1175869","name":"Jesús Belza","position":"Right-Back","dateOfBirth":"Feb 26, 2004","age":"20","nationality":["Spain"],"height":"1,68m","foot":"right","joinedOn":"Aug 22, 2024","joined":"On loan from CD Tenerife until Jun 30, 2025","signedFrom":"CD Tenerife","contract":"Jun 30, 2025","marketValue":"€200k"},{"id":"253238","name":"Toni Arranz","position":"Central Midfield","dateOfBirth":"Jan 14, 1994","age":"30","nationality":["Spain"],"height":"1,88m","foot":"right","joinedOn":"Jul 1, 2024","joined":"Joined from UE Cornellà; date: Jul 1, 2024; fee: free transfer","signedFrom":"UE Cornellà","contract":"Jun 30, 2025","marketValue":"€200k"},{"id":"531498","name":"Alejandro Marcelo","position":"Central Midfield","dateOfBirth":"Nov 29, 1998","age":"25","nationality":["Spain"],"foot":"left","joinedOn":"Jul 28, 2021","signedFrom":"Córdoba CF B","contract":"Jun 30, 2025","marketValue":"€150k"},{"id":"327650","name":"Xemi Fernández","position":"Attacking Midfield","dateOfBirth":"Feb 2, 1995","age":"29","nationality":["Spain"],"height":"1,84m","foot":"right","joinedOn":"Aug 16, 2024","joined":"Joined from CF Intercity; date: Aug 16, 2024; fee: free transfer","signedFrom":"CF Intercity","contract":"Jun 30, 2025","marketValue":"€400k"},{"id":"722280","name":"Luismi Gutiérrez","position":"Attacking Midfield","dateOfBirth":"Feb 19, 1996","age":"28","nationality":["Spain"],"joinedOn":"Jan 4, 2024","signedFrom":"Vélez CF","contract":"Jun 30, 2025","marketValue":"€250k"},{"id":"434660","name":"Chema Núñez","position":"Attacking Midfield","dateOfBirth":"Sep 16, 1997","age":"26","nationality":["Spain"],"height":"1,75m","foot":"left","joinedOn":"Jul 12, 2023","signedFrom":"Real Unión Club","contract":"Jun 30, 2025","marketValue":"€250k"},{"id":"147318","name":"Tomás Lanzini","position":"Attacking Midfield","dateOfBirth":"Nov 25, 1991","age":"32","nationality":["Argentina","Italy"],"height":"1,75m","foot":"right","joinedOn":"Aug 11, 2022","signedFrom":"Without Club","contract":"Jun 30, 2025","marketValue":"€100k"},{"id":"1120845","name":"Topo","position":"Attacking Midfield","dateOfBirth":"Sep 17, 2002","age":"21","nationality":["Spain"],"joinedOn":"Jul 1, 2023","signedFrom":"Antequera CF B","contract":"Jun 30, 2025","marketValue":"€50k"},{"id":"995574","name":"Jeremie Obounet Moussango","position":"Left Winger","dateOfBirth":"Aug 17, 2002","age":"22","nationality":["Gabon"],"height":"1,80m","foot":"right","joinedOn":"Jul 25, 2024","joined":"Joined from Diósgyőri VTK; date: Jul 25, 2024; fee: free transfer","signedFrom":"Diósgyőri VTK","contract":"Jun 30, 2025","marketValue":"€200k"},{"id":"409472","name":"Ousama Siddiki","position":"Right Winger","dateOfBirth":"Apr 13, 1998","age":"26","nationality":["Morocco","Spain"],"height":"1,79m","joinedOn":"Jul 1, 2024","joined":"Joined from UD Melilla; date: Jul 1, 2024; fee: free transfer","signedFrom":"UD Melilla","contract":"Jun 30, 2025","marketValue":"€200k"},{"id":"45567","name":"Jonathan Biabiany","position":"Right Winger","dateOfBirth":"Apr 28, 1988","age":"36","nationality":["France","Guadeloupe"],"height":"1,77m","foot":"right","joinedOn":"Jul 30, 2024","joined":"Joined from San Fernando CD; date: Jul 30, 2024; fee: free transfer","signedFrom":"San Fernando CD","contract":"Jun 30, 2025","marketValue":"€200k"},{"id":"697818","name":"Marcelo dos Santos","position":"Centre-Forward","dateOfBirth":"Jul 27, 1997","age":"27","nationality":["Brazil"],"height":"1,87m","foot":"right","joinedOn":"Aug 7, 2024","joined":"Joined from San Fernando CD; date: Aug 7, 2024; fee: free transfer","signedFrom":"San Fernando CD","contract":"Jun 30, 2025","marketValue":"€150k"},{"id":"523999","name":"Iñaki Elejalde","position":"Centre-Forward","dateOfBirth":"Jan 20, 1999","age":"25","nationality":["Spain"],"height":"1,76m","joinedOn":"Jul 1, 2024","joined":"Joined from Mérida AD; date: Jul 1, 2024; fee: free transfer","signedFrom":"Mérida AD","contract":"Jun 30, 2025","marketValue":"€150k"},{"id":"1151630","name":"Álex Rubio","position":"Centre-Forward","dateOfBirth":"Jul 25, 2002","age":"22","nationality":["Spain"],"height":"1,75m","foot":"right","joinedOn":"Aug 26, 2024","joined":"Joined from Real Murcia CF; date: Aug 26, 2024; fee: ?","signedFrom":"Real Murcia CF","contract":"Jun 30, 2025","marketValue":"€100k"}],"updatedAt":"2024-08-31T21:46:44.796459"}