{"id":"39","url":"/1-fsv-mainz-05/startseite/verein/39","name":"1.FSV Mainz 05","officialName":"1. Fußball- und Sportverein Mainz 05","image":"https://tmssl.akamaized.net/images/wappen/big/39.png","legalForm":"e.V.","addressLine1":"Isaac-Fulda-Allee 5","addressLine2":"55124 Mainz","addressLine3":"Germany","tel":"+49 6131 37550-0","fax":"+49 6131 37550-33","website":"www.mainz05.de","foundedOn":"Mar 16, 1905","members":"20.000","membersDate":"May 24, 2024","otherSports":["Handball","Tischtennis"],"colors":["#FF0000","#FFFFFF"],"stadiumName":"Mewa Arena","stadiumSeats":"33305","currentTransferRecord":"+€30.95m","currentMarketValue":"€75.35m","squad":{"size":"24","averageAge":"26.6","foreigners":"10","nationalTeamPlayers":"6"},"league":{"id":"L1","name":"Bundesliga","countryID":"4","countryName":"Germany","tier":"First Tier"},"historicalCrests":["https://tmssl.akamaized.net/images/wappen/medium/39_1400617157.png","https://tmssl.akamaized.net/images/wappen/medium/39_1400617479.png","https://tmssl.akamaized.net/images/wappen/medium/39_1566637084.png"],"updatedAt":"2024-08-26T21:30:26.836685"}