{"id":"12181","url":"/san-fernando-cd/startseite/verein/12181","name":"San Fernando CD","officialName":"San Fernando Club Deportivo","image":"https://tmssl.akamaized.net//images/wappen/big/12181.png","addressLine1":"Calle Maria de los Dolores s/n","addressLine2":"11100 San Fernando","addressLine3":"Spain","tel":"956 88 47 85","fax":"956 88 47 85","website":"https://sfcd.es/","foundedOn":"Jun 30, 2009","stadiumName":"Iberoamericano Bahía Sur","stadiumSeats":"6471","currentTransferRecord":"+-0","currentMarketValue":"€2.30m","squad":{"size":"20","averageAge":"26.7","foreigners":"2","nationalTeamPlayers":"1"},"league":{"id":"E4G4","name":"Segunda Federación - Grupo IV","countryID":"1","countryName":"Spain","tier":"Fourth Tier"},"updatedAt":"2024-09-04T19:48:30.267493"}