{"id":"16602","url":"/ub-conquense/startseite/verein/16602","name":"UB Conquense","officialName":"Unión Balompédica Conquense","image":"https://tmssl.akamaized.net//images/wappen/big/16602.png","addressLine1":"Calle Ramón y Cajal 47","addressLine2":"16004 Cuenca","addressLine3":"Spain","website":"www.ubconquense.es","foundedOn":"Nov 30, 1945","colors":["#000000","#FFFFFF"],"stadiumName":"La Fuensanta","stadiumSeats":"3550","currentTransferRecord":"+-0","currentMarketValue":"€700k","squad":{"size":"20","averageAge":"25.4","foreigners":"2","nationalTeamPlayers":"0"},"league":{"id":"E4G5","name":"Segunda Federación - Grupo V","countryID":"1","countryName":"Spain","tier":"Fourth Tier"},"updatedAt":"2024-09-04T19:50:26.197821"}