{"id":"50684","url":"/cd-coria/startseite/verein/50684","name":"CD Coria","officialName":"Club Deportivo Coria","image":"https://tmssl.akamaized.net//images/wappen/big/50684.png","addressLine2":"10800 Coria","addressLine3":"Spain","tel":"+34 644 46 24 55","website":"cdcoria.es.tl/","foundedOn":"Aug 6, 1969","members":"700","membersDate":"Jan 4, 2018","colors":["#1accc6","#1accc6"],"stadiumName":"La Isla","stadiumSeats":"3000","currentTransferRecord":"+-0","currentMarketValue":"€1.00m","squad":{"size":"22","averageAge":"25.7","foreigners":"3","nationalTeamPlayers":"0"},"league":{"id":"E4G5","name":"Segunda Federación - Grupo V","countryID":"1","countryName":"Spain","tier":"Fourth Tier"},"updatedAt":"2024-09-04T19:50:22.516111"}